instagram_tail-0.1.0.dist-info/METADATA
instagram_tail-0.1.0.dist-info/WHEEL
instagram_tail-0.1.0.dist-info/entry_points.txt
instagram_tail/__init__.py
instagram_tail/_instagram_api.py
instagram_tail/_model.py
instagram_tail/_params_service.py
instagram_tail/_parsers.py
instagram_tail/instagram_clients/__init__.py
instagram_tail/instagram_clients/instagram_client.py
instagram_tail/instagram_clients/instagram_client_async.py
instagram_tail-0.1.0.dist-info/RECORD
