Metadata-Version: 2.1
Name: instagram_tail
Version: 0.1.0
Summary: Instagram data collection library
Author-Email: shapranov dmitrii <shapranov.work@gmail.com>
License: MIT
Requires-Python: >=3.10
Requires-Dist: httpx>=0.28.1
Requires-Dist: beautifulsoup4>=4.13.3
